st_gridtable/__init__.py
st_gridtable/example.py
st_gridtable/rdkit-example_.py
st_gridtable/frontend/build/index.html
st_gridtable/frontend/build/smiles.csv
st_gridtable/frontend/build/assets/index-BbTsl4R3.js
st_gridtable/frontend/build/assets/index-DepCpngw.css
streamlit_gridtable-0.1.0.dist-info/licenses/LICENSE
streamlit_gridtable-0.1.0.dist-info/METADATA
streamlit_gridtable-0.1.0.dist-info/WHEEL
streamlit_gridtable-0.1.0.dist-info/top_level.txt
streamlit_gridtable-0.1.0.dist-info/RECORD
