Metadata-Version: 2.4
Name: streamlit-gridtable
Version: 0.1.0
Summary: Streamlit custom component: DataTables (React) wrapper
Author: junmae
License-Expression: MIT
Project-URL: Homepage, https://github.com/junmae/streamlit-grid-table
Project-URL: Source, https://github.com/junmae/streamlit-grid-table
Project-URL: Issues, https://github.com/junmae/streamlit-grid-table/issues
Keywords: streamlit,component,datatable,react
Classifier: Programming Language :: Python :: 3
Classifier: Operating System :: OS Independent
Classifier: Development Status :: 3 - Alpha
Classifier: Topic :: Software Development :: Libraries
Requires-Python: >=3.7
License-File: LICENSE
Requires-Dist: streamlit>=0.63
Provides-Extra: devel
Requires-Dist: wheel; extra == "devel"
Requires-Dist: pytest==7.4.0; extra == "devel"
Requires-Dist: playwright==1.48.0; extra == "devel"
Requires-Dist: requests==2.31.0; extra == "devel"
Requires-Dist: pytest-playwright-snapshot==1.0; extra == "devel"
Requires-Dist: pytest-rerunfailures==12.0; extra == "devel"
Dynamic: license-file
